ultrafastultrafast/RK_core.py
ultrafastultrafast/TA_5th_order_example.py
ultrafastultrafast/TA_5th_order_isotropic_average_example.py
ultrafastultrafast/TA_example.py
ultrafastultrafast/TA_isotropic_average_example.py
ultrafastultrafast/__init__.py
ultrafastultrafast/core.py
ultrafastultrafast/dipole_pruning.py
ultrafastultrafast/signals/RK_TA_example.py
ultrafastultrafast/signals/TA_5th_order_example.py
ultrafastultrafast/signals/TA_5th_order_isotropic_average_example.py
ultrafastultrafast/signals/TA_example.py
ultrafastultrafast/signals/TA_isotropic_average_example.py
ultrafastultrafast/signals/TDFS_example.py
ultrafastultrafast/signals/__init__.py
ultrafastultrafast/signals/analyze_TA_example.py
ultrafastultrafast/signals/plotting_tools.py
ultrafastultrafast/signals/signal_processing.py
ultrafastultrafast/vibronic_eigenstates/__init__.py
ultrafastultrafast/vibronic_eigenstates/base_class.py
ultrafastultrafast/vibronic_eigenstates/dipole_operator.py
ultrafastultrafast/vibronic_eigenstates/eigen_generator.py
ultrafastultrafast/vibronic_eigenstates/eigenstates.py
ultrafastultrafast/vibronic_eigenstates/params_converter.py
ultrafastultrafast/vibronic_eigenstates/simple_eigen_generator.py
ultrafastultrafast-0.2.0.dist-info/LICENSE
ultrafastultrafast-0.2.0.dist-info/METADATA
ultrafastultrafast-0.2.0.dist-info/WHEEL
ultrafastultrafast-0.2.0.dist-info/top_level.txt
ultrafastultrafast-0.2.0.dist-info/RECORD
