Metadata-Version: 2.1
Name: ultrafastultrafast
Version: 0.2.0
Summary: Package for simulating nonlinear optical spectra
Home-page: https://github.com/peterarose/ultrafastultrafast/
Author: Peter A. Rose and Jacob J. Krich
Author-email: peter.rose56@gmail.com
License: UNKNOWN
Keywords: nonlinear optical spectroscopy
Platform: UNKNOWN
Classifier: Development Status :: 3 - Alpha
Classifier: Intended Audience :: Science/Research
Classifier: Topic :: Scientific/Engineering :: Physics
Classifier: License :: OSI Approved :: MIT License
Classifier: Programming Language :: Python :: 3 :: Only
Requires-Python: >=3.5
Requires-Dist: numpy
Requires-Dist: matplotlib
Requires-Dist: pyfftw
Requires-Dist: scipy (>=1)
Requires-Dist: pyyaml
